yflib/__init__.py
yflib/_common.py
yflib/_dayEnd.py
yflib/functions.py
yflib/indicators/_BBANDS.py
yflib/indicators/_CCI.py
yflib/indicators/_EMA.py
yflib/indicators/_MACD.py
yflib/indicators/_OBV.py
yflib/indicators/_RSI.py
yflib/indicators/_SMA.py
yflib/indicators/_STOCH.py
yflib/indicators/_STOCHRSI.py
YFLIB-1.0.2.dist-info/METADATA
YFLIB-1.0.2.dist-info/WHEEL
YFLIB-1.0.2.dist-info/entry_points.txt
YFLIB-1.0.2.dist-info/top_level.txt
YFLIB-1.0.2.dist-info/RECORD
