Metadata-Version: 2.1
Name: YFLIB
Version: 1.0.2
Summary: Read the latest README.md
Home-page: https://github.com/SharkFinRice/Python_YFLib
Author: Dev
Author-email: alvinhoidam1128@gmail.com
License: MIT
Platform: UNKNOWN
Classifier: License :: OSI Approved :: MIT License
Classifier: Programming Language :: Python :: 3
Classifier: Programming Language :: Python :: 3.8
Requires-Dist: feedparser
Requires-Dist: html2text
